{"pool_id": "0x40ad08f17cd034694820edfe497de240f9ec1fec", "snapped_at": "2025-08-12T17:11:19.794609+00:00", "block_number": 10946515, "is_full": false, "current_tick": 192283, "sqrt_price": "1185904350750257097752717646888443", "fee_bps": 500, "tvl_usd": 2485.887990121245, "volume24h_usd": 5259.981015460167, "ticks": [{"tick_index": 191160, "liquidity_net": "147658838666789", "active_liquidity": "147658838666789"}, {"tick_index": 191940, "liquidity_net": "208316288660971", "active_liquidity": "355975127327760"}, {"tick_index": 192120, "liquidity_net": "25540291622889", "active_liquidity": "381515418950649"}, {"tick_index": 192180, "liquidity_net": "0", "active_liquidity": "381515418950649"}, {"tick_index": 192300, "liquidity_net": "0", "active_liquidity": "381515418950649"}, {"tick_index": 192420, "liquidity_net": "0", "active_liquidity": "381515418950649"}, {"tick_index": 192480, "liquidity_net": "0", "active_liquidity": "381515418950649"}, {"tick_index": 192600, "liquidity_net": "362117767676547", "active_liquidity": "743633186627196"}, {"tick_index": 192780, "liquidity_net": "0", "active_liquidity": "743633186627196"}, {"tick_index": 192840, "liquidity_net": "-208316288660971", "active_liquidity": "535316897966225"}, {"tick_index": 192960, "liquidity_net": "0", "active_liquidity": "535316897966225"}, {"tick_index": 193020, "liquidity_net": "-362117767676547", "active_liquidity": "173199130289678"}, {"tick_index": 193080, "liquidity_net": "0", "active_liquidity": "173199130289678"}, {"tick_index": 193140, "liquidity_net": "-25540291622889", "active_liquidity": "147658838666789"}, {"tick_index": 193260, "liquidity_net": "0", "active_liquidity": "147658838666789"}, {"tick_index": 193380, "liquidity_net": "0", "active_liquidity": "147658838666789"}, {"tick_index": 193440, "liquidity_net": "0", "active_liquidity": "147658838666789"}, {"tick_index": 193500, "liquidity_net": "0", "active_liquidity": "147658838666789"}, {"tick_index": 193620, "liquidity_net": "0", "active_liquidity": "147658838666789"}, {"tick_index": 193680, "liquidity_net": "0", "active_liquidity": "147658838666789"}, {"tick_index": 193740, "liquidity_net": "0", "active_liquidity": "147658838666789"}, {"tick_index": 193800, "liquidity_net": "0", "active_liquidity": "147658838666789"}, {"tick_index": 193860, "liquidity_net": "-147658838666789", "active_liquidity": "0"}, {"tick_index": 193920, "liquidity_net": "0", "active_liquidity": "0"}, {"tick_index": 193980, "liquidity_net": "0", "active_liquidity": "0"}, {"tick_index": 194040, "liquidity_net": "0", "active_liquidity": "0"}, {"tick_index": 194100, "liquidity_net": "0", "active_liquidity": "0"}, {"tick_index": 194160, "liquidity_net": "0", "active_liquidity": "0"}, {"tick_index": 194220, "liquidity_net": "0", "active_liquidity": "0"}, {"tick_index": 194280, "liquidity_net": "0", "active_liquidity": "0"}, {"tick_index": 194340, "liquidity_net": "0", "active_liquidity": "0"}, {"tick_index": 194400, "liquidity_net": "0", "active_liquidity": "0"}, {"tick_index": 194460, "liquidity_net": "0", "active_liquidity": "0"}, {"tick_index": 194520, "liquidity_net": "0", "active_liquidity": "0"}, {"tick_index": 194580, "liquidity_net": "0", "active_liquidity": "0"}, {"tick_index": 194640, "liquidity_net": "0", "active_liquidity": "0"}, {"tick_index": 194700, "liquidity_net": "0", "active_liquidity": "0"}, {"tick_index": 194760, "liquidity_net": "0", "active_liquidity": "0"}, {"tick_index": 194820, "liquidity_net": "0", "active_liquidity": "0"}, {"tick_index": 194880, "liquidity_net": "0", "active_liquidity": "0"}, {"tick_index": 194940, "liquidity_net": "0", "active_liquidity": "0"}, {"tick_index": 195000, "liquidity_net": "0", "active_liquidity": "0"}, {"tick_index": 195060, "liquidity_net": "0", "active_liquidity": "0"}, {"tick_index": 195120, "liquidity_net": "0", "active_liquidity": "0"}, {"tick_index": 195240, "liquidity_net": "0", "active_liquidity": "0"}, {"tick_index": 195300, "liquidity_net": "0", "active_liquidity": "0"}, {"tick_index": 195600, "liquidity_net": "0", "active_liquidity": "0"}]}